emd_falsify/__init__.py
emd_falsify/_version.py
emd_falsify/digitize.py
emd_falsify/emd.md
emd_falsify/emd.py
emd_falsify/memoize.py
emd_falsify/path_sampling.md
emd_falsify/path_sampling.py
emd_falsify/tasks.md
emd_falsify/tasks.py
emd_falsify/utils.py
emd_falsify/viz.md
emd_falsify/viz.py
emd_falsify/config/__init__.md
emd_falsify/config/__init__.py
emd_falsify/config/defaults.cfg
emd_falsify-1.0.1.dist-info/LICENSE
emd_falsify-1.0.1.dist-info/METADATA
emd_falsify-1.0.1.dist-info/WHEEL
emd_falsify-1.0.1.dist-info/top_level.txt
emd_falsify-1.0.1.dist-info/RECORD
