Metadata-Version: 2.1
Name: emd-falsify
Version: 1.0.1
Summary: Original implementation of the EMD (empirical model discrepancy) model comparison criterion
Author-email: Alexandre René <arene010@uottawa.ca>
License: MPL 2.0
Project-URL: Documentation, https://alcrene.github.io/emd-falsify/
Project-URL: Bug Tracker, https://github.com/alcrene/emd-falsify/issues
Project-URL: Source, https://github.com/alcrene/emd-falsify
Keywords: empirical model discrepancy,bayes factor,inference,model comparison,bayesian
Classifier: Development Status :: 3 - Alpha
Classifier: License :: OSI Approved :: Mozilla Public License 2.0 (MPL 2.0)
Classifier: Intended Audience :: Science/Research
Classifier: Programming Language :: Python :: 3
Classifier: Programming Language :: Python :: 3 :: Only
Classifier: Programming Language :: Python :: 3.9
Classifier: Programming Language :: Python :: 3.10
Classifier: Programming Language :: Python :: 3.11
Classifier: Topic :: Scientific/Engineering
Classifier: Topic :: Scientific/Engineering :: Mathematics
Requires-Python: >=3.7
License-File: LICENSE
Requires-Dist: more-itertools
Requires-Dist: numpy
Requires-Dist: scipy >=1.7
Requires-Dist: pydantic >=1.8.2
Requires-Dist: tqdm
Requires-Dist: joblib
Requires-Dist: scityping
Requires-Dist: valconfig >=0.1.2
Provides-Extra: doc
Requires-Dist: pandas ; extra == 'doc'
Requires-Dist: matplotlib ; extra == 'doc'
Requires-Dist: seaborn ; extra == 'doc'
Requires-Dist: holoviews ; extra == 'doc'
Requires-Dist: addict ; extra == 'doc'
Requires-Dist: jupyter-book >=0.14 ; extra == 'doc'
Requires-Dist: sphinx-proof ; extra == 'doc'
Requires-Dist: jupytext ; extra == 'doc'
Requires-Dist: ipykernel ; extra == 'doc'
Requires-Dist: bokeh ; extra == 'doc'
Requires-Dist: jupyter-bokeh ; extra == 'doc'
Requires-Dist: selenium ; extra == 'doc'
Requires-Dist: phantomjs ; extra == 'doc'
Requires-Dist: pillow ; extra == 'doc'
Requires-Dist: ghp-import ; extra == 'doc'
Provides-Extra: test
Requires-Dist: pytest ; extra == 'test'
Provides-Extra: viz
Requires-Dist: pandas ; extra == 'viz'
Requires-Dist: matplotlib ; extra == 'viz'
Requires-Dist: seaborn ; extra == 'viz'
Requires-Dist: holoviews ; extra == 'viz'
